MANIFEST.in
ez_setup.py
setup.py
FastProject/CLI.py
FastProject/DataTypes.py
FastProject/FileIO.py
FastProject/Filters.py
FastProject/Global.py
FastProject/HtmlViewer.py
FastProject/Interactive.py
FastProject/NormalizationMethods.py
FastProject/Pipelines.py
FastProject/Projections.py
FastProject/SigScoreMethods.py
FastProject/Signatures.py
FastProject/SubSample.py
FastProject/Transforms.py
FastProject/__init__.py
FastProject/_tsne_fix.py
FastProject/_version.py
FastProject/jsonIO.py
FastProject.egg-info/PKG-INFO
FastProject.egg-info/SOURCES.txt
FastProject.egg-info/dependency_links.txt
FastProject.egg-info/entry_points.txt
FastProject.egg-info/requires.txt
FastProject.egg-info/top_level.txt
FastProject/Housekeeping Genes/Ensemble Housekeeping.txt
FastProject/Housekeeping Genes/Gene Name Housekeeping.txt
FastProject/Tests/__init__.py
FastProject/Tests/full_battery.py
FastProject/Tests/test_JSON.py
FastProject/Tests/test_projections.py
FastProject/Tests/TestFiles/housekeeping.txt
FastProject/Tests/TestFiles/input_projection_RFormat_ok.txt
FastProject/Tests/TestFiles/input_projection_duplicate18and36_bad.txt
FastProject/Tests/TestFiles/input_projection_good.txt
FastProject/Tests/TestFiles/input_projection_header_ok.txt
FastProject/Tests/TestFiles/input_projection_header_ok2.txt
FastProject/Tests/TestFiles/input_projection_missing10and20_bad.txt
FastProject/Tests/TestFiles/input_projection_nan26and27_bad.txt
FastProject/Tests/TestFiles/input_projection_parseError26and28_bad.txt
FastProject/Tests/TestFiles/precomputed_sigs.txt
FastProject/Tests/TestFiles/sigsA.txt
FastProject/Tests/TestFiles/sigsB.txt
FastProject/Tests/TestFiles/sigsSmall.gmt
FastProject/Tests/TestFiles/smallData.txt
FastProject/Tests/TestFiles/weights.txt
FastProject/Utils/ProgressBar.py
FastProject/Utils/__init__.py
FastProject/Utils/em.py
FastProject/Utils/hdt.py
FastProject/Viewer Resources/Clustered_HeatMap.js
FastProject/Viewer Resources/ColorScatter.js
FastProject/Viewer Resources/HeatMap.js
FastProject/Viewer Resources/QC_Report.html
FastProject/Viewer Resources/Results.html
FastProject/Viewer Resources/Utilities.js
FastProject/Viewer Resources/bootstrap.css
FastProject/Viewer Resources/bootstrap.min.js
