Metadata-Version: 1.0
Name: FastProject
Version: 1.1.3
Summary: A python module for evaulating dimensionality reduction techniques on gene expression data.
Home-page: https://github.com/YosefLab/FastProject
Author: David DeTomaso
Author-email: David.DeTomaso@berkeley.edu
License: Free for Academic and Not-For-Profit Use, See Repository for Details
Keywords: Bioinformatics dimensionality reduction projection rna-seq
Platform: UNKNOWN
